thaibulksms_api/sms.py
thaibulksms_api-1.0.8.dist-info/METADATA
thaibulksms_api-1.0.8.dist-info/WHEEL
thaibulksms_api-1.0.8.dist-info/top_level.txt
thaibulksms_api-1.0.8.dist-info/RECORD
