Metadata-Version: 2.1
Name: thaibulksms-api
Version: 1.0.8
Summary: Thaibulksms API for send sms
Home-page: UNKNOWN
Author: thaibulksms_api
Author-email: apichart@1moby.com
License: thaibulksms
Platform: UNKNOWN
